pgstats/__init__.py
pgstats/management/__init__.py
pgstats/management/commands/__init__.py
pgstats/management/commands/snapshot_pgstats.py
pgstats/migrations/0001_initial.py
pgstats/migrations/__init__.py
pgstats/models.py
pgstats/py.typed
pgstats/version.py
django_pgstats-1.5.1.dist-info/LICENSE
django_pgstats-1.5.1.dist-info/METADATA
django_pgstats-1.5.1.dist-info/WHEEL
django_pgstats-1.5.1.dist-info/RECORD
